MANIFEST.in
README.md
requirements.txt
setup.py
nymbus/__init__.py
nymbus/__main__.py
nymbus.egg-info/PKG-INFO
nymbus.egg-info/SOURCES.txt
nymbus.egg-info/dependency_links.txt
nymbus.egg-info/entry_points.txt
nymbus.egg-info/requires.txt
nymbus.egg-info/top_level.txt
nymbus/cli/__init__.py
nymbus/cli/runner.py
nymbus/cli/setupper.py
nymbus/cli/console/__init__.py
nymbus/cli/console/output.py
nymbus/config/__init__.py
nymbus/config/environment.py
nymbus/config/envspec.py
nymbus/config/template.py
nymbus/config/components/__init__.py
nymbus/config/components/component.py
nymbus/config/components/step.py
nymbus/config/images/__init__.py
nymbus/config/images/bind.py
nymbus/config/images/image.py
nymbus/config/readers/__init__.py
nymbus/config/readers/combiner.py
nymbus/config/readers/reader.py
nymbus/tools/__init__.py
nymbus/tools/shell.py
nymbus/tools/system.py